{"year":2024,"scope":"congressional","contest_type":"labor_commissioner","meta":{"match_coverage_pct":97.03,"matched_precinct_keys":2583,"total_precinct_keys":2662,"source":"batch_shatter_vap_party_split","office":"NC COMMISSIONER OF LABOR","nongeo_allocation_mode":"precinct_candidate"},"general":{"results":{"1":{"dem_votes":194472,"rep_votes":182628,"other_votes":0,"total_votes":377100,"dem_candidate":"Braxton Winston II","rep_candidate":"Luke Farley","margin":-11844,"margin_pct":-3.14,"winner":"DEM","competitiveness":{"color":"#c6dbef"}},"2":{"dem_votes":244550,"rep_votes":156689,"other_votes":0,"total_votes":401239,"dem_candidate":"Braxton Winston II","rep_candidate":"Luke Farley","margin":-87861,"margin_pct":-21.9,"winner":"DEM","competitiveness":{"color":"#3182bd"}},"3":{"dem_votes":127568,"rep_votes":241894,"other_votes":0,"total_votes":369462,"dem_candidate":"Braxton Winston II","rep_candidate":"Luke Farley","margin":114326,"margin_pct":30.94,"winner":"REP","competitiveness":{"color":"#a50f15"}},"4":{"dem_votes":265745,"rep_votes":135690,"other_votes":0,"total_votes":401435,"dem_candidate":"Braxton Winston II","rep_candidate":"Luke Farley","margin":-130055,"margin_pct":-32.4,"winner":"DEM","competitiveness":{"color":"#08519c"}},"5":{"dem_votes":148827,"rep_votes":249298,"other_votes":0,"total_votes":398125,"dem_candidate":"Braxton Winston II","rep_candidate":"Luke Farley","margin":100471,"margin_pct":25.24,"winner":"REP","competitiveness":{"color":"#cb181d"}},"6":{"dem_votes":208014,"rep_votes":174686,"other_votes":0,"total_votes":382700,"dem_candidate":"Braxton Winston II","rep_candidate":"Luke Farley","margin":-33328,"margin_pct":-8.71,"winner":"DEM","competitiveness":{"color":"#9ecae1"}},"7":{"dem_votes":171870,"rep_votes":246651,"other_votes":0,"total_votes":418521,"dem_candidate":"Braxton Winston II","rep_candidate":"Luke Farley","margin":74781,"margin_pct":17.87,"winner":"REP","competitiveness":{"color":"#ef3b2c"}},"8":{"dem_votes":124107,"rep_votes":273960,"other_votes":0,"total_votes":398067,"dem_candidate":"Braxton Winston II","rep_candidate":"Luke Farley","margin":149853,"margin_pct":37.65,"winner":"REP","competitiveness":{"color":"#a50f15"}},"9":{"dem_votes":148921,"rep_votes":191649,"other_votes":0,"total_votes":340570,"dem_candidate":"Braxton Winston II","rep_candidate":"Luke Farley","margin":42728,"margin_pct":12.55,"winner":"REP","competitiveness":{"color":"#ef3b2c"}},"10":{"dem_votes":118579,"rep_votes":280360,"other_votes":0,"total_votes":398939,"dem_candidate":"Braxton Winston II","rep_candidate":"Luke Farley","margin":161781,"margin_pct":40.55,"winner":"REP","competitiveness":{"color":"#67000d"}},"11":{"dem_votes":191501,"rep_votes":237311,"other_votes":0,"total_votes":428812,"dem_candidate":"Braxton Winston II","rep_candidate":"Luke Farley","margin":45810,"margin_pct":10.68,"winner":"REP","competitiveness":{"color":"#ef3b2c"}},"12":{"dem_votes":234963,"rep_votes":132559,"other_votes":0,"total_votes":367522,"dem_candidate":"Braxton Winston II","rep_candidate":"Luke Farley","margin":-102404,"margin_pct":-27.86,"winner":"DEM","competitiveness":{"color":"#3182bd"}},"13":{"dem_votes":214109,"rep_votes":220131,"other_votes":0,"total_votes":434240,"dem_candidate":"Braxton Winston II","rep_candidate":"Luke Farley","margin":6022,"margin_pct":1.39,"winner":"REP","competitiveness":{"color":"#fcae91"}},"14":{"dem_votes":208029,"rep_votes":180824,"other_votes":0,"total_votes":388853,"dem_candidate":"Braxton Winston II","rep_candidate":"Luke Farley","margin":-27205,"margin_pct":-7.0,"winner":"DEM","competitiveness":{"color":"#9ecae1"}}}}}