{"year":2012,"scope":"state_house","contest_type":"treasurer","meta":{"match_coverage_pct":100.0,"matched_precinct_keys":3054,"total_precinct_keys":3054},"general":{"results":{"064":{"dem_votes":13930,"rep_votes":18809,"other_votes":0,"total_votes":32739,"dem_candidate":"","rep_candidate":"","margin":4879,"margin_pct":14.9,"winner":"REP","competitiveness":{"color":"#ef3b2c"}},"063":{"dem_votes":17797,"rep_votes":14082,"other_votes":0,"total_votes":31879,"dem_candidate":"","rep_candidate":"","margin":-3715,"margin_pct":-11.65,"winner":"DEM","competitiveness":{"color":"#6baed6"}},"094":{"dem_votes":14047,"rep_votes":24484,"other_votes":0,"total_votes":38531,"dem_candidate":"","rep_candidate":"","margin":10437,"margin_pct":27.09,"winner":"REP","competitiveness":{"color":"#cb181d"}},"093":{"dem_votes":18974,"rep_votes":20802,"other_votes":0,"total_votes":39776,"dem_candidate":"","rep_candidate":"","margin":1828,"margin_pct":4.6,"winner":"REP","competitiveness":{"color":"#fcae91"}},"055":{"dem_votes":20349,"rep_votes":15834,"other_votes":0,"total_votes":36183,"dem_candidate":"","rep_candidate":"","margin":-4515,"margin_pct":-12.48,"winner":"DEM","competitiveness":{"color":"#6baed6"}},"085":{"dem_votes":14162,"rep_votes":23596,"other_votes":0,"total_votes":37758,"dem_candidate":"","rep_candidate":"","margin":9434,"margin_pct":24.99,"winner":"REP","competitiveness":{"color":"#cb181d"}},"079":{"dem_votes":19375,"rep_votes":21572,"other_votes":0,"total_votes":40947,"dem_candidate":"","rep_candidate":"","margin":2197,"margin_pct":5.37,"winner":"REP","competitiveness":{"color":"#fcae91"}},"023":{"dem_votes":34027,"rep_votes":13796,"other_votes":0,"total_votes":47823,"dem_candidate":"","rep_candidate":"","margin":-20231,"margin_pct":-42.3,"winner":"DEM","competitiveness":{"color":"#08306b"}},"022":{"dem_votes":22190,"rep_votes":18325,"other_votes":0,"total_votes":40515,"dem_candidate":"","rep_candidate":"","margin":-3865,"margin_pct":-9.54,"winner":"DEM","competitiveness":{"color":"#9ecae1"}},"017":{"dem_votes":14801,"rep_votes":19066,"other_votes":0,"total_votes":33867,"dem_candidate":"","rep_candidate":"","margin":4265,"margin_pct":12.59,"winner":"REP","competitiveness":{"color":"#ef3b2c"}},"019":{"dem_votes":14937,"rep_votes":22246,"other_votes":0,"total_votes":37183,"dem_candidate":"","rep_candidate":"","margin":7309,"margin_pct":19.66,"winner":"REP","competitiveness":{"color":"#ef3b2c"}},"114":{"dem_votes":24942,"rep_votes":16200,"other_votes":0,"total_votes":41142,"dem_candidate":"","rep_candidate":"","margin":-8742,"margin_pct":-21.25,"winner":"DEM","competitiveness":{"color":"#3182bd"}},"116":{"dem_votes":23527,"rep_votes":17455,"other_votes":0,"total_votes":40982,"dem_candidate":"","rep_candidate":"","margin":-6072,"margin_pct":-14.82,"winner":"DEM","competitiveness":{"color":"#6baed6"}},"115":{"dem_votes":21847,"rep_votes":17225,"other_votes":0,"total_votes":39072,"dem_candidate":"","rep_candidate":"","margin":-4622,"margin_pct":-11.83,"winner":"DEM","competitiveness":{"color":"#6baed6"}},"086":{"dem_votes":16170,"rep_votes":18972,"other_votes":0,"total_votes":35142,"dem_candidate":"","rep_candidate":"","margin":2802,"margin_pct":7.97,"winner":"REP","competitiveness":{"color":"#fb6a4a"}},"082":{"dem_votes":14299,"rep_votes":16155,"other_votes":0,"total_votes":30454,"dem_candidate":"","rep_candidate":"","margin":1856,"margin_pct":6.09,"winner":"REP","competitiveness":{"color":"#fb6a4a"}},"073":{"dem_votes":12808,"rep_votes":14471,"other_votes":0,"total_votes":27279,"dem_candidate":"","rep_candidate":"","margin":1663,"margin_pct":6.1,"winner":"REP","competitiveness":{"color":"#fb6a4a"}},"083":{"dem_votes":15866,"rep_votes":23378,"other_votes":0,"total_votes":39244,"dem_candidate":"","rep_candidate":"","margin":7512,"margin_pct":19.14,"winner":"REP","competitiveness":{"color":"#ef3b2c"}},"087":{"dem_votes":14226,"rep_votes":21312,"other_votes":0,"total_votes":35538,"dem_candidate":"","rep_candidate":"","margin":7086,"margin_pct":19.94,"winner":"REP","competitiveness":{"color":"#ef3b2c"}},"005":{"dem_votes":23585,"rep_votes":13685,"other_votes":0,"total_votes":37270,"dem_candidate":"","rep_candidate":"","margin":-9900,"margin_pct":-26.56,"winner":"DEM","competitiveness":{"color":"#3182bd"}},"013":{"dem_votes":13310,"rep_votes":25313,"other_votes":0,"total_votes":38623,"dem_candidate":"","rep_candidate":"","margin":12003,"margin_pct":31.08,"winner":"REP","competitiveness":{"color":"#a50f15"}},"050":{"dem_votes":33201,"rep_votes":15671,"other_votes":0,"total_votes":48872,"dem_candidate":"","rep_candidate":"","margin":-17530,"margin_pct":-35.87,"winner":"DEM","competitiveness":{"color":"#08519c"}},"089":{"dem_votes":13844,"rep_votes":23396,"other_votes":0,"total_votes":37240,"dem_candidate":"","rep_candidate":"","margin":9552,"margin_pct":25.65,"winner":"REP","competitiveness":{"color":"#cb181d"}},"096":{"dem_votes":15980,"rep_votes":20576,"other_votes":0,"total_votes":36556,"dem_candidate":"","rep_candidate":"","margin":4596,"margin_pct":12.57,"winner":"REP","competitiveness":{"color":"#ef3b2c"}},"054":{"dem_votes":25061,"rep_votes":25602,"other_votes":0,"total_votes":50663,"dem_candidate":"","rep_candidate":"","margin":541,"margin_pct":1.07,"winner":"REP","competitiveness":{"color":"#fcae91"}},"120":{"dem_votes":13572,"rep_votes":23142,"other_votes":0,"total_votes":36714,"dem_candidate":"","rep_candidate":"","margin":9570,"margin_pct":26.07,"winner":"REP","competitiveness":{"color":"#cb181d"}},"001":{"dem_votes":18992,"rep_votes":19746,"other_votes":0,"total_votes":38738,"dem_candidate":"","rep_candidate":"","margin":754,"margin_pct":1.95,"winner":"REP","competitiveness":{"color":"#fcae91"}},"111":{"dem_votes":15928,"rep_votes":19379,"other_votes":0,"total_votes":35307,"dem_candidate":"","rep_candidate":"","margin":3451,"margin_pct":9.77,"winner":"REP","competitiveness":{"color":"#fb6a4a"}},"110":{"dem_votes":17439,"rep_votes":20626,"other_votes":0,"total_votes":38065,"dem_candidate":"","rep_candidate":"","margin":3187,"margin_pct":8.37,"winner":"REP","competitiveness":{"color":"#fb6a4a"}},"046":{"dem_votes":20666,"rep_votes":13788,"other_votes":0,"total_votes":34454,"dem_candidate":"","rep_candidate":"","margin":-6878,"margin_pct":-19.96,"winner":"DEM","competitiveness":{"color":"#6baed6"}},"003":{"dem_votes":17490,"rep_votes":22107,"other_votes":0,"total_votes":39597,"dem_candidate":"","rep_candidate":"","margin":4617,"margin_pct":11.66,"winner":"REP","competitiveness":{"color":"#ef3b2c"}},"044":{"dem_votes":31704,"rep_votes":15732,"other_votes":0,"total_votes":47436,"dem_candidate":"","rep_candidate":"","margin":-15972,"margin_pct":-33.67,"winner":"DEM","competitiveness":{"color":"#08519c"}},"043":{"dem_votes":21160,"rep_votes":14923,"other_votes":0,"total_votes":36083,"dem_candidate":"","rep_candidate":"","margin":-6237,"margin_pct":-17.29,"winner":"DEM","competitiveness":{"color":"#6baed6"}},"045":{"dem_votes":15857,"rep_votes":9947,"other_votes":0,"total_votes":25804,"dem_candidate":"","rep_candidate":"","margin":-5910,"margin_pct":-22.9,"winner":"DEM","competitiveness":{"color":"#3182bd"}},"042":{"dem_votes":9795,"rep_votes":3722,"other_votes":0,"total_votes":13517,"dem_candidate":"","rep_candidate":"","margin":-6073,"margin_pct":-44.93,"winner":"DEM","competitiveness":{"color":"#08306b"}},"081":{"dem_votes":13106,"rep_votes":20169,"other_votes":0,"total_votes":33275,"dem_candidate":"","rep_candidate":"","margin":7063,"margin_pct":21.23,"winner":"REP","competitiveness":{"color":"#cb181d"}},"080":{"dem_votes":11905,"rep_votes":23521,"other_votes":0,"total_votes":35426,"dem_candidate":"","rep_candidate":"","margin":11616,"margin_pct":32.79,"winner":"REP","competitiveness":{"color":"#a50f15"}},"077":{"dem_votes":13911,"rep_votes":26882,"other_votes":0,"total_votes":40793,"dem_candidate":"","rep_candidate":"","margin":12971,"margin_pct":31.8,"winner":"REP","competitiveness":{"color":"#a50f15"}},"004":{"dem_votes":17453,"rep_votes":17275,"other_votes":0,"total_votes":34728,"dem_candidate":"","rep_candidate":"","margin":-178,"margin_pct":-0.51,"winner":"DEM","competitiveness":{"color":"#e1f5fe"}},"030":{"dem_votes":43019,"rep_votes":11333,"other_votes":0,"total_votes":54352,"dem_candidate":"","rep_candidate":"","margin":-31686,"margin_pct":-58.3,"winner":"DEM","competitiveness":{"color":"#08306b"}},"029":{"dem_votes":25714,"rep_votes":7110,"other_votes":0,"total_votes":32824,"dem_candidate":"","rep_candidate":"","margin":-18604,"margin_pct":-56.68,"winner":"DEM","competitiveness":{"color":"#08306b"}},"031":{"dem_votes":17673,"rep_votes":4474,"other_votes":0,"total_votes":22147,"dem_candidate":"","rep_candidate":"","margin":-13199,"margin_pct":-59.6,"winner":"DEM","competitiveness":{"color":"#08306b"}},"002":{"dem_votes":33323,"rep_votes":15619,"other_votes":0,"total_votes":48942,"dem_candidate":"","rep_candidate":"","margin":-17704,"margin_pct":-36.17,"winner":"DEM","competitiveness":{"color":"#08519c"}},"074":{"dem_votes":19749,"rep_votes":22933,"other_votes":0,"total_votes":42682,"dem_candidate":"","rep_candidate":"","margin":3184,"margin_pct":7.46,"winner":"REP","competitiveness":{"color":"#fb6a4a"}},"072":{"dem_votes":27969,"rep_votes":11161,"other_votes":0,"total_votes":39130,"dem_candidate":"","rep_candidate":"","margin":-16808,"margin_pct":-42.95,"winner":"DEM","competitiveness":{"color":"#08306b"}},"071":{"dem_votes":24695,"rep_votes":10173,"other_votes":0,"total_votes":34868,"dem_candidate":"","rep_candidate":"","margin":-14522,"margin_pct":-41.65,"winner":"DEM","competitiveness":{"color":"#08306b"}},"075":{"dem_votes":13263,"rep_votes":16595,"other_votes":0,"total_votes":29858,"dem_candidate":"","rep_candidate":"","margin":3332,"margin_pct":11.16,"winner":"REP","competitiveness":{"color":"#ef3b2c"}},"091":{"dem_votes":17182,"rep_votes":24571,"other_votes":0,"total_votes":41753,"dem_candidate":"","rep_candidate":"","margin":7389,"margin_pct":17.7,"winner":"REP","competitiveness":{"color":"#ef3b2c"}},"062":{"dem_votes":20618,"rep_votes":23741,"other_votes":0,"total_votes":44359,"dem_candidate":"","rep_candidate":"","margin":3123,"margin_pct":7.04,"winner":"REP","competitiveness":{"color":"#fb6a4a"}},"007":{"dem_votes":18182,"rep_votes":15472,"other_votes":0,"total_votes":33654,"dem_candidate":"","rep_candidate":"","margin":-2710,"margin_pct":-8.05,"winner":"DEM","competitiveness":{"color":"#9ecae1"}},"109":{"dem_votes":15293,"rep_votes":20580,"other_votes":0,"total_votes":35873,"dem_candidate":"","rep_candidate":"","margin":5287,"margin_pct":14.74,"winner":"REP","competitiveness":{"color":"#ef3b2c"}},"108":{"dem_votes":12070,"rep_votes":16574,"other_votes":0,"total_votes":28644,"dem_candidate":"","rep_candidate":"","margin":4504,"margin_pct":15.72,"winner":"REP","competitiveness":{"color":"#ef3b2c"}},"032":{"dem_votes":26862,"rep_votes":12510,"other_votes":0,"total_votes":39372,"dem_candidate":"","rep_candidate":"","margin":-14352,"margin_pct":-36.45,"winner":"DEM","competitiveness":{"color":"#08519c"}},"012":{"dem_votes":21804,"rep_votes":18077,"other_votes":0,"total_votes":39881,"dem_candidate":"","rep_candidate":"","margin":-3727,"margin_pct":-9.35,"winner":"DEM","competitiveness":{"color":"#9ecae1"}},"057":{"dem_votes":23662,"rep_votes":20045,"other_votes":0,"total_votes":43707,"dem_candidate":"","rep_candidate":"","margin":-3617,"margin_pct":-8.28,"winner":"DEM","competitiveness":{"color":"#9ecae1"}},"061":{"dem_votes":34023,"rep_votes":8220,"other_votes":0,"total_votes":42243,"dem_candidate":"","rep_candidate":"","margin":-25803,"margin_pct":-61.08,"winner":"DEM","competitiveness":{"color":"#08306b"}},"058":{"dem_votes":28179,"rep_votes":10220,"other_votes":0,"total_votes":38399,"dem_candidate":"","rep_candidate":"","margin":-17959,"margin_pct":-46.77,"winner":"DEM","competitiveness":{"color":"#08306b"}},"059":{"dem_votes":19326,"rep_votes":18521,"other_votes":0,"total_votes":37847,"dem_candidate":"","rep_candidate":"","margin":-805,"margin_pct":-2.13,"winner":"DEM","competitiveness":{"color":"#c6dbef"}},"060":{"dem_votes":22736,"rep_votes":13606,"other_votes":0,"total_votes":36342,"dem_candidate":"","rep_candidate":"","margin":-9130,"margin_pct":-25.12,"winner":"DEM","competitiveness":{"color":"#3182bd"}},"027":{"dem_votes":34007,"rep_votes":11932,"other_votes":0,"total_votes":45939,"dem_candidate":"","rep_candidate":"","margin":-22075,"margin_pct":-48.05,"winner":"DEM","competitiveness":{"color":"#08306b"}},"053":{"dem_votes":19815,"rep_votes":23654,"other_votes":0,"total_votes":43469,"dem_candidate":"","rep_candidate":"","margin":3839,"margin_pct":8.83,"winner":"REP","competitiveness":{"color":"#fb6a4a"}},"006":{"dem_votes":5997,"rep_votes":5788,"other_votes":0,"total_votes":11785,"dem_candidate":"","rep_candidate":"","margin":-209,"margin_pct":-1.77,"winner":"DEM","competitiveness":{"color":"#c6dbef"}},"118":{"dem_votes":17371,"rep_votes":18626,"other_votes":0,"total_votes":35997,"dem_candidate":"","rep_candidate":"","margin":1255,"margin_pct":3.49,"winner":"REP","competitiveness":{"color":"#fcae91"}},"117":{"dem_votes":15244,"rep_votes":24288,"other_votes":0,"total_votes":39532,"dem_candidate":"","rep_candidate":"","margin":9044,"margin_pct":22.88,"winner":"REP","competitiveness":{"color":"#cb181d"}},"113":{"dem_votes":16382,"rep_votes":23179,"other_votes":0,"total_votes":39561,"dem_candidate":"","rep_candidate":"","margin":6797,"margin_pct":17.18,"winner":"REP","competitiveness":{"color":"#ef3b2c"}},"048":{"dem_votes":19345,"rep_votes":10225,"other_votes":0,"total_votes":29570,"dem_candidate":"","rep_candidate":"","margin":-9120,"margin_pct":-30.84,"winner":"DEM","competitiveness":{"color":"#08519c"}},"084":{"dem_votes":16319,"rep_votes":20116,"other_votes":0,"total_votes":36435,"dem_candidate":"","rep_candidate":"","margin":3797,"margin_pct":10.42,"winner":"REP","competitiveness":{"color":"#ef3b2c"}},"095":{"dem_votes":10683,"rep_votes":18593,"other_votes":0,"total_votes":29276,"dem_candidate":"","rep_candidate":"","margin":7910,"margin_pct":27.02,"winner":"REP","competitiveness":{"color":"#cb181d"}},"119":{"dem_votes":18249,"rep_votes":19018,"other_votes":0,"total_votes":37267,"dem_candidate":"","rep_candidate":"","margin":769,"margin_pct":2.06,"winner":"REP","competitiveness":{"color":"#fcae91"}},"028":{"dem_votes":17018,"rep_votes":20627,"other_votes":0,"total_votes":37645,"dem_candidate":"","rep_candidate":"","margin":3609,"margin_pct":9.59,"winner":"REP","competitiveness":{"color":"#fb6a4a"}},"026":{"dem_votes":10343,"rep_votes":12808,"other_votes":0,"total_votes":23151,"dem_candidate":"","rep_candidate":"","margin":2465,"margin_pct":10.65,"winner":"REP","competitiveness":{"color":"#ef3b2c"}},"051":{"dem_votes":15608,"rep_votes":14877,"other_votes":0,"total_votes":30485,"dem_candidate":"","rep_candidate":"","margin":-731,"margin_pct":-2.4,"winner":"DEM","competitiveness":{"color":"#c6dbef"}},"097":{"dem_votes":13120,"rep_votes":21859,"other_votes":0,"total_votes":34979,"dem_candidate":"","rep_candidate":"","margin":8739,"margin_pct":24.98,"winner":"REP","competitiveness":{"color":"#cb181d"}},"102":{"dem_votes":24882,"rep_votes":7604,"other_votes":0,"total_votes":32486,"dem_candidate":"","rep_candidate":"","margin":-17278,"margin_pct":-53.19,"winner":"DEM","competitiveness":{"color":"#08306b"}},"099":{"dem_votes":22581,"rep_votes":4981,"other_votes":0,"total_votes":27562,"dem_candidate":"","rep_candidate":"","margin":-17600,"margin_pct":-63.86,"winner":"DEM","competitiveness":{"color":"#08306b"}},"112":{"dem_votes":19931,"rep_votes":12247,"other_votes":0,"total_votes":32178,"dem_candidate":"","rep_candidate":"","margin":-7684,"margin_pct":-23.88,"winner":"DEM","competitiveness":{"color":"#3182bd"}},"100":{"dem_votes":22056,"rep_votes":6892,"other_votes":0,"total_votes":28948,"dem_candidate":"","rep_candidate":"","margin":-15164,"margin_pct":-52.38,"winner":"DEM","competitiveness":{"color":"#08306b"}},"088":{"dem_votes":19898,"rep_votes":9479,"other_votes":0,"total_votes":29377,"dem_candidate":"","rep_candidate":"","margin":-10419,"margin_pct":-35.47,"winner":"DEM","competitiveness":{"color":"#08519c"}},"101":{"dem_votes":25121,"rep_votes":7945,"other_votes":0,"total_votes":33066,"dem_candidate":"","rep_candidate":"","margin":-17176,"margin_pct":-51.94,"winner":"DEM","competitiveness":{"color":"#08306b"}},"107":{"dem_votes":27827,"rep_votes":7131,"other_votes":0,"total_votes":34958,"dem_candidate":"","rep_candidate":"","margin":-20696,"margin_pct":-59.2,"winner":"DEM","competitiveness":{"color":"#08306b"}},"104":{"dem_votes":18668,"rep_votes":20822,"other_votes":0,"total_votes":39490,"dem_candidate":"","rep_candidate":"","margin":2154,"margin_pct":5.45,"winner":"REP","competitiveness":{"color":"#fcae91"}},"092":{"dem_votes":18318,"rep_votes":8839,"other_votes":0,"total_votes":27157,"dem_candidate":"","rep_candidate":"","margin":-9479,"margin_pct":-34.9,"winner":"DEM","competitiveness":{"color":"#08519c"}},"103":{"dem_votes":17700,"rep_votes":22114,"other_votes":0,"total_votes":39814,"dem_candidate":"","rep_candidate":"","margin":4414,"margin_pct":11.09,"winner":"REP","competitiveness":{"color":"#ef3b2c"}},"105":{"dem_votes":17868,"rep_votes":18461,"other_votes":0,"total_votes":36329,"dem_candidate":"","rep_candidate":"","margin":593,"margin_pct":1.63,"winner":"REP","competitiveness":{"color":"#fcae91"}},"098":{"dem_votes":14628,"rep_votes":19240,"other_votes":0,"total_votes":33868,"dem_candidate":"","rep_candidate":"","margin":4612,"margin_pct":13.62,"winner":"REP","competitiveness":{"color":"#ef3b2c"}},"106":{"dem_votes":20147,"rep_votes":11257,"other_votes":0,"total_votes":31404,"dem_candidate":"","rep_candidate":"","margin":-8890,"margin_pct":-28.31,"winner":"DEM","competitiveness":{"color":"#3182bd"}},"067":{"dem_votes":16763,"rep_votes":21178,"other_votes":0,"total_votes":37941,"dem_candidate":"","rep_candidate":"","margin":4415,"margin_pct":11.64,"winner":"REP","competitiveness":{"color":"#ef3b2c"}},"078":{"dem_votes":12579,"rep_votes":22301,"other_votes":0,"total_votes":34880,"dem_candidate":"","rep_candidate":"","margin":9722,"margin_pct":27.87,"winner":"REP","competitiveness":{"color":"#cb181d"}},"052":{"dem_votes":19175,"rep_votes":15635,"other_votes":0,"total_votes":34810,"dem_candidate":"","rep_candidate":"","margin":-3540,"margin_pct":-10.17,"winner":"DEM","competitiveness":{"color":"#6baed6"}},"025":{"dem_votes":27492,"rep_votes":20026,"other_votes":0,"total_votes":47518,"dem_candidate":"","rep_candidate":"","margin":-7466,"margin_pct":-15.71,"winner":"DEM","competitiveness":{"color":"#6baed6"}},"018":{"dem_votes":23241,"rep_votes":18283,"other_votes":0,"total_votes":41524,"dem_candidate":"","rep_candidate":"","margin":-4958,"margin_pct":-11.94,"winner":"DEM","competitiveness":{"color":"#6baed6"}},"020":{"dem_votes":16082,"rep_votes":21603,"other_votes":0,"total_votes":37685,"dem_candidate":"","rep_candidate":"","margin":5521,"margin_pct":14.65,"winner":"REP","competitiveness":{"color":"#ef3b2c"}},"015":{"dem_votes":8761,"rep_votes":12608,"other_votes":0,"total_votes":21369,"dem_candidate":"","rep_candidate":"","margin":3847,"margin_pct":18.0,"winner":"REP","competitiveness":{"color":"#ef3b2c"}},"014":{"dem_votes":7482,"rep_votes":10247,"other_votes":0,"total_votes":17729,"dem_candidate":"","rep_candidate":"","margin":2765,"margin_pct":15.6,"winner":"REP","competitiveness":{"color":"#ef3b2c"}},"016":{"dem_votes":13278,"rep_votes":19028,"other_votes":0,"total_votes":32306,"dem_candidate":"","rep_candidate":"","margin":5750,"margin_pct":17.8,"winner":"REP","competitiveness":{"color":"#ef3b2c"}},"056":{"dem_votes":25976,"rep_votes":8411,"other_votes":0,"total_votes":34387,"dem_candidate":"","rep_candidate":"","margin":-17565,"margin_pct":-51.08,"winner":"DEM","competitiveness":{"color":"#08306b"}},"008":{"dem_votes":24384,"rep_votes":17970,"other_votes":0,"total_votes":42354,"dem_candidate":"","rep_candidate":"","margin":-6414,"margin_pct":-15.14,"winner":"DEM","competitiveness":{"color":"#6baed6"}},"009":{"dem_votes":18693,"rep_votes":14969,"other_votes":0,"total_votes":33662,"dem_candidate":"","rep_candidate":"","margin":-3724,"margin_pct":-11.06,"winner":"DEM","competitiveness":{"color":"#6baed6"}},"070":{"dem_votes":8398,"rep_votes":18947,"other_votes":0,"total_votes":27345,"dem_candidate":"","rep_candidate":"","margin":10549,"margin_pct":38.58,"winner":"REP","competitiveness":{"color":"#a50f15"}},"047":{"dem_votes":20727,"rep_votes":8439,"other_votes":0,"total_votes":29166,"dem_candidate":"","rep_candidate":"","margin":-12288,"margin_pct":-42.13,"winner":"DEM","competitiveness":{"color":"#08306b"}},"065":{"dem_votes":18989,"rep_votes":20953,"other_votes":0,"total_votes":39942,"dem_candidate":"","rep_candidate":"","margin":1964,"margin_pct":4.92,"winner":"REP","competitiveness":{"color":"#fcae91"}},"076":{"dem_votes":18274,"rep_votes":18684,"other_votes":0,"total_votes":36958,"dem_candidate":"","rep_candidate":"","margin":410,"margin_pct":1.11,"winner":"REP","competitiveness":{"color":"#fcae91"}},"090":{"dem_votes":13387,"rep_votes":20216,"other_votes":0,"total_votes":33603,"dem_candidate":"","rep_candidate":"","margin":6829,"margin_pct":20.32,"winner":"REP","competitiveness":{"color":"#cb181d"}},"069":{"dem_votes":13619,"rep_votes":22884,"other_votes":0,"total_votes":36503,"dem_candidate":"","rep_candidate":"","margin":9265,"margin_pct":25.38,"winner":"REP","competitiveness":{"color":"#cb181d"}},"068":{"dem_votes":9327,"rep_votes":18964,"other_votes":0,"total_votes":28291,"dem_candidate":"","rep_candidate":"","margin":9637,"margin_pct":34.06,"winner":"REP","competitiveness":{"color":"#a50f15"}},"011":{"dem_votes":24315,"rep_votes":15753,"other_votes":0,"total_votes":40068,"dem_candidate":"","rep_candidate":"","margin":-8562,"margin_pct":-21.37,"winner":"DEM","competitiveness":{"color":"#3182bd"}},"049":{"dem_votes":29281,"rep_votes":18051,"other_votes":0,"total_votes":47332,"dem_candidate":"","rep_candidate":"","margin":-11230,"margin_pct":-23.73,"winner":"DEM","competitiveness":{"color":"#3182bd"}},"034":{"dem_votes":33725,"rep_votes":21420,"other_votes":0,"total_votes":55145,"dem_candidate":"","rep_candidate":"","margin":-12305,"margin_pct":-22.31,"winner":"DEM","competitiveness":{"color":"#3182bd"}},"038":{"dem_votes":24612,"rep_votes":10846,"other_votes":0,"total_votes":35458,"dem_candidate":"","rep_candidate":"","margin":-13766,"margin_pct":-38.82,"winner":"DEM","competitiveness":{"color":"#08519c"}},"040":{"dem_votes":35208,"rep_votes":26417,"other_votes":0,"total_votes":61625,"dem_candidate":"","rep_candidate":"","margin":-8791,"margin_pct":-14.27,"winner":"DEM","competitiveness":{"color":"#6baed6"}},"041":{"dem_votes":26993,"rep_votes":18294,"other_votes":0,"total_votes":45287,"dem_candidate":"","rep_candidate":"","margin":-8699,"margin_pct":-19.21,"winner":"DEM","competitiveness":{"color":"#6baed6"}},"033":{"dem_votes":20855,"rep_votes":14079,"other_votes":0,"total_votes":34934,"dem_candidate":"","rep_candidate":"","margin":-6776,"margin_pct":-19.4,"winner":"DEM","competitiveness":{"color":"#6baed6"}},"066":{"dem_votes":21503,"rep_votes":12661,"other_votes":0,"total_votes":34164,"dem_candidate":"","rep_candidate":"","margin":-8842,"margin_pct":-25.88,"winner":"DEM","competitiveness":{"color":"#3182bd"}},"036":{"dem_votes":15217,"rep_votes":11325,"other_votes":0,"total_votes":26542,"dem_candidate":"","rep_candidate":"","margin":-3892,"margin_pct":-14.66,"winner":"DEM","competitiveness":{"color":"#6baed6"}},"037":{"dem_votes":14342,"rep_votes":11158,"other_votes":0,"total_votes":25500,"dem_candidate":"","rep_candidate":"","margin":-3184,"margin_pct":-12.49,"winner":"DEM","competitiveness":{"color":"#6baed6"}},"035":{"dem_votes":13577,"rep_votes":10712,"other_votes":0,"total_votes":24289,"dem_candidate":"","rep_candidate":"","margin":-2865,"margin_pct":-11.8,"winner":"DEM","competitiveness":{"color":"#6baed6"}},"039":{"dem_votes":13796,"rep_votes":9315,"other_votes":0,"total_votes":23111,"dem_candidate":"","rep_candidate":"","margin":-4481,"margin_pct":-19.39,"winner":"DEM","competitiveness":{"color":"#6baed6"}},"021":{"dem_votes":6376,"rep_votes":4522,"other_votes":0,"total_votes":10898,"dem_candidate":"","rep_candidate":"","margin":-1854,"margin_pct":-17.01,"winner":"DEM","competitiveness":{"color":"#6baed6"}},"010":{"dem_votes":17960,"rep_votes":16814,"other_votes":0,"total_votes":34774,"dem_candidate":"","rep_candidate":"","margin":-1146,"margin_pct":-3.3,"winner":"DEM","competitiveness":{"color":"#c6dbef"}},"024":{"dem_votes":22789,"rep_votes":14993,"other_votes":0,"total_votes":37782,"dem_candidate":"","rep_candidate":"","margin":-7796,"margin_pct":-20.63,"winner":"DEM","competitiveness":{"color":"#3182bd"}}}}}