{
  "year": 2024,
  "scope": "congressional",
  "contest_type": "governor",
  "meta": {
    "match_coverage_pct": 97.03,
    "matched_precinct_keys": 2583,
    "total_precinct_keys": 2662,
    "source": "batch_shatter_vap_party_split",
    "office": "NC GOVERNOR",
    "nongeo_allocation_mode": "precinct_candidate"
  },
  "general": {
    "results": {
      "1": {
        "dem_votes": 197869,
        "rep_votes": 164512,
        "other_votes": 12182,
        "total_votes": 374563,
        "dem_candidate": "Josh Stein",
        "rep_candidate": "Mark Robinson",
        "margin": -33357,
        "margin_pct": -8.91,
        "winner": "DEM",
        "competitiveness": {
          "color": "#9ecae1"
        }
      },
      "2": {
        "dem_votes": 309170,
        "rep_votes": 90141,
        "other_votes": 22476,
        "total_votes": 421787,
        "dem_candidate": "Josh Stein",
        "rep_candidate": "Mark Robinson",
        "margin": -219029,
        "margin_pct": -51.93,
        "winner": "DEM",
        "competitiveness": {
          "color": "#08306b"
        }
      },
      "3": {
        "dem_votes": 170844,
        "rep_votes": 183731,
        "other_votes": 19494,
        "total_votes": 374069,
        "dem_candidate": "Josh Stein",
        "rep_candidate": "Mark Robinson",
        "margin": 12887,
        "margin_pct": 3.45,
        "winner": "REP",
        "competitiveness": {
          "color": "#fcae91"
        }
      },
      "4": {
        "dem_votes": 328867,
        "rep_votes": 78220,
        "other_votes": 17734,
        "total_votes": 424821,
        "dem_candidate": "Josh Stein",
        "rep_candidate": "Mark Robinson",
        "margin": -250647,
        "margin_pct": -59.0,
        "winner": "DEM",
        "competitiveness": {
          "color": "#08306b"
        }
      },
      "5": {
        "dem_votes": 192084,
        "rep_votes": 186462,
        "other_votes": 19136,
        "total_votes": 397682,
        "dem_candidate": "Josh Stein",
        "rep_candidate": "Mark Robinson",
        "margin": -5622,
        "margin_pct": -1.41,
        "winner": "DEM",
        "competitiveness": {
          "color": "#c6dbef"
        }
      },
      "6": {
        "dem_votes": 194184,
        "rep_votes": 177513,
        "other_votes": 22721,
        "total_votes": 394418,
        "dem_candidate": "Josh Stein",
        "rep_candidate": "Mark Robinson",
        "margin": -16671,
        "margin_pct": -4.23,
        "winner": "DEM",
        "competitiveness": {
          "color": "#c6dbef"
        }
      },
      "7": {
        "dem_votes": 222236,
        "rep_votes": 187546,
        "other_votes": 24849,
        "total_votes": 434631,
        "dem_candidate": "Josh Stein",
        "rep_candidate": "Mark Robinson",
        "margin": -34690,
        "margin_pct": -7.98,
        "winner": "DEM",
        "competitiveness": {
          "color": "#9ecae1"
        }
      },
      "8": {
        "dem_votes": 183691,
        "rep_votes": 192761,
        "other_votes": 20480,
        "total_votes": 396932,
        "dem_candidate": "Josh Stein",
        "rep_candidate": "Mark Robinson",
        "margin": 9070,
        "margin_pct": 2.29,
        "winner": "REP",
        "competitiveness": {
          "color": "#fcae91"
        }
      },
      "9": {
        "dem_votes": 178273,
        "rep_votes": 171133,
        "other_votes": 19267,
        "total_votes": 368673,
        "dem_candidate": "Josh Stein",
        "rep_candidate": "Mark Robinson",
        "margin": -7140,
        "margin_pct": -1.94,
        "winner": "DEM",
        "competitiveness": {
          "color": "#c6dbef"
        }
      },
      "10": {
        "dem_votes": 197380,
        "rep_votes": 188805,
        "other_votes": 21636,
        "total_votes": 407821,
        "dem_candidate": "Josh Stein",
        "rep_candidate": "Mark Robinson",
        "margin": -8575,
        "margin_pct": -2.1,
        "winner": "DEM",
        "competitiveness": {
          "color": "#c6dbef"
        }
      },
      "11": {
        "dem_votes": 223130,
        "rep_votes": 190792,
        "other_votes": 19525,
        "total_votes": 433447,
        "dem_candidate": "Josh Stein",
        "rep_candidate": "Mark Robinson",
        "margin": -32338,
        "margin_pct": -7.46,
        "winner": "DEM",
        "competitiveness": {
          "color": "#9ecae1"
        }
      },
      "12": {
        "dem_votes": 274686,
        "rep_votes": 62856,
        "other_votes": 17142,
        "total_votes": 354684,
        "dem_candidate": "Josh Stein",
        "rep_candidate": "Mark Robinson",
        "margin": -211830,
        "margin_pct": -59.72,
        "winner": "DEM",
        "competitiveness": {
          "color": "#08306b"
        }
      },
      "13": {
        "dem_votes": 201032,
        "rep_votes": 184990,
        "other_votes": 22589,
        "total_votes": 408611,
        "dem_candidate": "Josh Stein",
        "rep_candidate": "Mark Robinson",
        "margin": -16042,
        "margin_pct": -3.93,
        "winner": "DEM",
        "competitiveness": {
          "color": "#c6dbef"
        }
      },
      "14": {
        "dem_votes": 196049,
        "rep_votes": 181848,
        "other_votes": 21511,
        "total_votes": 399408,
        "dem_candidate": "Josh Stein",
        "rep_candidate": "Mark Robinson",
        "margin": -14201,
        "margin_pct": -3.56,
        "winner": "DEM",
        "competitiveness": {
          "color": "#c6dbef"
        }
      }
    }
  }
}
