{
  "year": 2008,
  "scope": "congressional",
  "contest_type": "nc_court_of_appeals_judge_tyson_seat",
  "meta": {
    "match_coverage_pct": 73.12,
    "matched_precinct_keys": 2021,
    "total_precinct_keys": 2764,
    "source": "batch_shatter_vap_party_split",
    "office": "COURT OF APPEALS JUDGE (Tyson Seat)",
    "nongeo_allocation_mode": "precinct_candidate"
  },
  "general": {
    "results": {
      "1": {
        "dem_votes": 0,
        "rep_votes": 0,
        "other_votes": 240379,
        "total_votes": 240379,
        "dem_candidate": "",
        "rep_candidate": "",
        "margin": 0,
        "margin_pct": 0.0,
        "winner": "TIE",
        "competitiveness": {
          "color": "#f7f7f7"
        }
      },
      "2": {
        "dem_votes": 0,
        "rep_votes": 0,
        "other_votes": 210248,
        "total_votes": 210248,
        "dem_candidate": "",
        "rep_candidate": "",
        "margin": 0,
        "margin_pct": 0.0,
        "winner": "TIE",
        "competitiveness": {
          "color": "#f7f7f7"
        }
      },
      "3": {
        "dem_votes": 0,
        "rep_votes": 0,
        "other_votes": 197159,
        "total_votes": 197159,
        "dem_candidate": "",
        "rep_candidate": "",
        "margin": 0,
        "margin_pct": 0.0,
        "winner": "TIE",
        "competitiveness": {
          "color": "#f7f7f7"
        }
      },
      "4": {
        "dem_votes": 0,
        "rep_votes": 0,
        "other_votes": 204622,
        "total_votes": 204622,
        "dem_candidate": "",
        "rep_candidate": "",
        "margin": 0,
        "margin_pct": 0.0,
        "winner": "TIE",
        "competitiveness": {
          "color": "#f7f7f7"
        }
      },
      "5": {
        "dem_votes": 0,
        "rep_votes": 0,
        "other_votes": 240203,
        "total_votes": 240203,
        "dem_candidate": "",
        "rep_candidate": "",
        "margin": 0,
        "margin_pct": 0.0,
        "winner": "TIE",
        "competitiveness": {
          "color": "#f7f7f7"
        }
      },
      "6": {
        "dem_votes": 0,
        "rep_votes": 0,
        "other_votes": 208141,
        "total_votes": 208141,
        "dem_candidate": "",
        "rep_candidate": "",
        "margin": 0,
        "margin_pct": 0.0,
        "winner": "TIE",
        "competitiveness": {
          "color": "#f7f7f7"
        }
      },
      "7": {
        "dem_votes": 0,
        "rep_votes": 0,
        "other_votes": 212311,
        "total_votes": 212311,
        "dem_candidate": "",
        "rep_candidate": "",
        "margin": 0,
        "margin_pct": 0.0,
        "winner": "TIE",
        "competitiveness": {
          "color": "#f7f7f7"
        }
      },
      "8": {
        "dem_votes": 0,
        "rep_votes": 0,
        "other_votes": 198812,
        "total_votes": 198812,
        "dem_candidate": "",
        "rep_candidate": "",
        "margin": 0,
        "margin_pct": 0.0,
        "winner": "TIE",
        "competitiveness": {
          "color": "#f7f7f7"
        }
      },
      "9": {
        "dem_votes": 0,
        "rep_votes": 0,
        "other_votes": 208984,
        "total_votes": 208984,
        "dem_candidate": "",
        "rep_candidate": "",
        "margin": 0,
        "margin_pct": 0.0,
        "winner": "TIE",
        "competitiveness": {
          "color": "#f7f7f7"
        }
      },
      "10": {
        "dem_votes": 0,
        "rep_votes": 0,
        "other_votes": 222458,
        "total_votes": 222458,
        "dem_candidate": "",
        "rep_candidate": "",
        "margin": 0,
        "margin_pct": 0.0,
        "winner": "TIE",
        "competitiveness": {
          "color": "#f7f7f7"
        }
      },
      "11": {
        "dem_votes": 0,
        "rep_votes": 0,
        "other_votes": 231447,
        "total_votes": 231447,
        "dem_candidate": "",
        "rep_candidate": "",
        "margin": 0,
        "margin_pct": 0.0,
        "winner": "TIE",
        "competitiveness": {
          "color": "#f7f7f7"
        }
      },
      "12": {
        "dem_votes": 0,
        "rep_votes": 0,
        "other_votes": 179435,
        "total_votes": 179435,
        "dem_candidate": "",
        "rep_candidate": "",
        "margin": 0,
        "margin_pct": 0.0,
        "winner": "TIE",
        "competitiveness": {
          "color": "#f7f7f7"
        }
      },
      "13": {
        "dem_votes": 0,
        "rep_votes": 0,
        "other_votes": 186195,
        "total_votes": 186195,
        "dem_candidate": "",
        "rep_candidate": "",
        "margin": 0,
        "margin_pct": 0.0,
        "winner": "TIE",
        "competitiveness": {
          "color": "#f7f7f7"
        }
      },
      "14": {
        "dem_votes": 0,
        "rep_votes": 0,
        "other_votes": 197185,
        "total_votes": 197185,
        "dem_candidate": "",
        "rep_candidate": "",
        "margin": 0,
        "margin_pct": 0.0,
        "winner": "TIE",
        "competitiveness": {
          "color": "#f7f7f7"
        }
      }
    }
  }
}
