{
  "year": 2024,
  "scope": "state_senate",
  "contest_type": "superintendent",
  "meta": {
    "match_coverage_pct": 97.03,
    "matched_precinct_keys": 2583,
    "total_precinct_keys": 2662,
    "source": "batch_shatter_vap_party_split",
    "office": "NC SUPERINTENDENT OF PUBLIC INSTRUCTION",
    "nongeo_allocation_mode": "precinct_candidate"
  },
  "general": {
    "results": {
      "1": {
        "dem_votes": 49114,
        "rep_votes": 61085,
        "other_votes": 0,
        "total_votes": 110199,
        "dem_candidate": "Maurice (Mo) Green",
        "rep_candidate": "Michele Morrow",
        "margin": 11971,
        "margin_pct": 10.86,
        "winner": "REP",
        "competitiveness": {
          "color": "#ef3b2c"
        }
      },
      "2": {
        "dem_votes": 51627,
        "rep_votes": 61556,
        "other_votes": 0,
        "total_votes": 113183,
        "dem_candidate": "Maurice (Mo) Green",
        "rep_candidate": "Michele Morrow",
        "margin": 9929,
        "margin_pct": 8.77,
        "winner": "REP",
        "competitiveness": {
          "color": "#fb6a4a"
        }
      },
      "3": {
        "dem_votes": 46963,
        "rep_votes": 60357,
        "other_votes": 0,
        "total_votes": 107320,
        "dem_candidate": "Maurice (Mo) Green",
        "rep_candidate": "Michele Morrow",
        "margin": 13394,
        "margin_pct": 12.48,
        "winner": "REP",
        "competitiveness": {
          "color": "#ef3b2c"
        }
      },
      "4": {
        "dem_votes": 48711,
        "rep_votes": 52109,
        "other_votes": 0,
        "total_votes": 100820,
        "dem_candidate": "Maurice (Mo) Green",
        "rep_candidate": "Michele Morrow",
        "margin": 3398,
        "margin_pct": 3.37,
        "winner": "REP",
        "competitiveness": {
          "color": "#fcae91"
        }
      },
      "5": {
        "dem_votes": 63579,
        "rep_votes": 45314,
        "other_votes": 0,
        "total_votes": 108893,
        "dem_candidate": "Maurice (Mo) Green",
        "rep_candidate": "Michele Morrow",
        "margin": -18265,
        "margin_pct": -16.77,
        "winner": "DEM",
        "competitiveness": {
          "color": "#6baed6"
        }
      },
      "6": {
        "dem_votes": 27168,
        "rep_votes": 49996,
        "other_votes": 0,
        "total_votes": 77164,
        "dem_candidate": "Maurice (Mo) Green",
        "rep_candidate": "Michele Morrow",
        "margin": 22828,
        "margin_pct": 29.58,
        "winner": "REP",
        "competitiveness": {
          "color": "#cb181d"
        }
      },
      "7": {
        "dem_votes": 59271,
        "rep_votes": 59497,
        "other_votes": 0,
        "total_votes": 118768,
        "dem_candidate": "Maurice (Mo) Green",
        "rep_candidate": "Michele Morrow",
        "margin": 226,
        "margin_pct": 0.19,
        "winner": "REP",
        "competitiveness": {
          "color": "#f7f7f7"
        }
      },
      "8": {
        "dem_votes": 61926,
        "rep_votes": 84497,
        "other_votes": 0,
        "total_votes": 146423,
        "dem_candidate": "Maurice (Mo) Green",
        "rep_candidate": "Michele Morrow",
        "margin": 22571,
        "margin_pct": 15.41,
        "winner": "REP",
        "competitiveness": {
          "color": "#ef3b2c"
        }
      },
      "9": {
        "dem_votes": 41294,
        "rep_votes": 65162,
        "other_votes": 0,
        "total_votes": 106456,
        "dem_candidate": "Maurice (Mo) Green",
        "rep_candidate": "Michele Morrow",
        "margin": 23868,
        "margin_pct": 22.42,
        "winner": "REP",
        "competitiveness": {
          "color": "#cb181d"
        }
      },
      "10": {
        "dem_votes": 51772,
        "rep_votes": 68766,
        "other_votes": 0,
        "total_votes": 120538,
        "dem_candidate": "Maurice (Mo) Green",
        "rep_candidate": "Michele Morrow",
        "margin": 16994,
        "margin_pct": 14.1,
        "winner": "REP",
        "competitiveness": {
          "color": "#ef3b2c"
        }
      },
      "11": {
        "dem_votes": 57876,
        "rep_votes": 54917,
        "other_votes": 0,
        "total_votes": 112793,
        "dem_candidate": "Maurice (Mo) Green",
        "rep_candidate": "Michele Morrow",
        "margin": -2959,
        "margin_pct": -2.62,
        "winner": "DEM",
        "competitiveness": {
          "color": "#c6dbef"
        }
      },
      "12": {
        "dem_votes": 38837,
        "rep_votes": 54678,
        "other_votes": 0,
        "total_votes": 93515,
        "dem_candidate": "Maurice (Mo) Green",
        "rep_candidate": "Michele Morrow",
        "margin": 15841,
        "margin_pct": 16.94,
        "winner": "REP",
        "competitiveness": {
          "color": "#ef3b2c"
        }
      },
      "13": {
        "dem_votes": 70347,
        "rep_votes": 54825,
        "other_votes": 0,
        "total_votes": 125172,
        "dem_candidate": "Maurice (Mo) Green",
        "rep_candidate": "Michele Morrow",
        "margin": -15522,
        "margin_pct": -12.4,
        "winner": "DEM",
        "competitiveness": {
          "color": "#6baed6"
        }
      },
      "14": {
        "dem_votes": 71097,
        "rep_votes": 22780,
        "other_votes": 0,
        "total_votes": 93877,
        "dem_candidate": "Maurice (Mo) Green",
        "rep_candidate": "Michele Morrow",
        "margin": -48317,
        "margin_pct": -51.47,
        "winner": "DEM",
        "competitiveness": {
          "color": "#08306b"
        }
      },
      "15": {
        "dem_votes": 83190,
        "rep_votes": 32633,
        "other_votes": 0,
        "total_votes": 115823,
        "dem_candidate": "Maurice (Mo) Green",
        "rep_candidate": "Michele Morrow",
        "margin": -50557,
        "margin_pct": -43.65,
        "winner": "DEM",
        "competitiveness": {
          "color": "#08306b"
        }
      },
      "16": {
        "dem_votes": 85472,
        "rep_votes": 37743,
        "other_votes": 0,
        "total_votes": 123215,
        "dem_candidate": "Maurice (Mo) Green",
        "rep_candidate": "Michele Morrow",
        "margin": -47729,
        "margin_pct": -38.74,
        "winner": "DEM",
        "competitiveness": {
          "color": "#08519c"
        }
      },
      "17": {
        "dem_votes": 63921,
        "rep_votes": 32415,
        "other_votes": 0,
        "total_votes": 96336,
        "dem_candidate": "Maurice (Mo) Green",
        "rep_candidate": "Michele Morrow",
        "margin": -31506,
        "margin_pct": -32.7,
        "winner": "DEM",
        "competitiveness": {
          "color": "#08519c"
        }
      },
      "18": {
        "dem_votes": 60436,
        "rep_votes": 53422,
        "other_votes": 0,
        "total_votes": 113858,
        "dem_candidate": "Maurice (Mo) Green",
        "rep_candidate": "Michele Morrow",
        "margin": -7014,
        "margin_pct": -6.16,
        "winner": "DEM",
        "competitiveness": {
          "color": "#9ecae1"
        }
      },
      "19": {
        "dem_votes": 58534,
        "rep_votes": 30182,
        "other_votes": 0,
        "total_votes": 88716,
        "dem_candidate": "Maurice (Mo) Green",
        "rep_candidate": "Michele Morrow",
        "margin": -28352,
        "margin_pct": -31.96,
        "winner": "DEM",
        "competitiveness": {
          "color": "#08519c"
        }
      },
      "20": {
        "dem_votes": 86930,
        "rep_votes": 32516,
        "other_votes": 0,
        "total_votes": 119446,
        "dem_candidate": "Maurice (Mo) Green",
        "rep_candidate": "Michele Morrow",
        "margin": -54414,
        "margin_pct": -45.56,
        "winner": "DEM",
        "competitiveness": {
          "color": "#08306b"
        }
      },
      "21": {
        "dem_votes": 44108,
        "rep_votes": 63728,
        "other_votes": 0,
        "total_votes": 107836,
        "dem_candidate": "Maurice (Mo) Green",
        "rep_candidate": "Michele Morrow",
        "margin": 19620,
        "margin_pct": 18.19,
        "winner": "REP",
        "competitiveness": {
          "color": "#ef3b2c"
        }
      },
      "22": {
        "dem_votes": 89702,
        "rep_votes": 19372,
        "other_votes": 0,
        "total_votes": 109074,
        "dem_candidate": "Maurice (Mo) Green",
        "rep_candidate": "Michele Morrow",
        "margin": -70330,
        "margin_pct": -64.48,
        "winner": "DEM",
        "competitiveness": {
          "color": "#08306b"
        }
      },
      "23": {
        "dem_votes": 79347,
        "rep_votes": 38534,
        "other_votes": 0,
        "total_votes": 117881,
        "dem_candidate": "Maurice (Mo) Green",
        "rep_candidate": "Michele Morrow",
        "margin": -40813,
        "margin_pct": -34.62,
        "winner": "DEM",
        "competitiveness": {
          "color": "#08519c"
        }
      },
      "24": {
        "dem_votes": 37059,
        "rep_votes": 43391,
        "other_votes": 0,
        "total_votes": 80450,
        "dem_candidate": "Maurice (Mo) Green",
        "rep_candidate": "Michele Morrow",
        "margin": 6332,
        "margin_pct": 7.87,
        "winner": "REP",
        "competitiveness": {
          "color": "#fb6a4a"
        }
      },
      "25": {
        "dem_votes": 50656,
        "rep_votes": 61890,
        "other_votes": 0,
        "total_votes": 112546,
        "dem_candidate": "Maurice (Mo) Green",
        "rep_candidate": "Michele Morrow",
        "margin": 11234,
        "margin_pct": 9.98,
        "winner": "REP",
        "competitiveness": {
          "color": "#fb6a4a"
        }
      },
      "26": {
        "dem_votes": 47744,
        "rep_votes": 65580,
        "other_votes": 0,
        "total_votes": 113324,
        "dem_candidate": "Maurice (Mo) Green",
        "rep_candidate": "Michele Morrow",
        "margin": 17836,
        "margin_pct": 15.74,
        "winner": "REP",
        "competitiveness": {
          "color": "#ef3b2c"
        }
      },
      "27": {
        "dem_votes": 71176,
        "rep_votes": 39242,
        "other_votes": 0,
        "total_votes": 110418,
        "dem_candidate": "Maurice (Mo) Green",
        "rep_candidate": "Michele Morrow",
        "margin": -31934,
        "margin_pct": -28.92,
        "winner": "DEM",
        "competitiveness": {
          "color": "#3182bd"
        }
      },
      "28": {
        "dem_votes": 81214,
        "rep_votes": 21985,
        "other_votes": 0,
        "total_votes": 103199,
        "dem_candidate": "Maurice (Mo) Green",
        "rep_candidate": "Michele Morrow",
        "margin": -59229,
        "margin_pct": -57.39,
        "winner": "DEM",
        "competitiveness": {
          "color": "#08306b"
        }
      },
      "29": {
        "dem_votes": 36910,
        "rep_votes": 67191,
        "other_votes": 0,
        "total_votes": 104101,
        "dem_candidate": "Maurice (Mo) Green",
        "rep_candidate": "Michele Morrow",
        "margin": 30281,
        "margin_pct": 29.09,
        "winner": "REP",
        "competitiveness": {
          "color": "#cb181d"
        }
      },
      "30": {
        "dem_votes": 37199,
        "rep_votes": 81190,
        "other_votes": 0,
        "total_votes": 118389,
        "dem_candidate": "Maurice (Mo) Green",
        "rep_candidate": "Michele Morrow",
        "margin": 43991,
        "margin_pct": 37.16,
        "winner": "REP",
        "competitiveness": {
          "color": "#a50f15"
        }
      },
      "31": {
        "dem_votes": 53644,
        "rep_votes": 72927,
        "other_votes": 0,
        "total_votes": 126571,
        "dem_candidate": "Maurice (Mo) Green",
        "rep_candidate": "Michele Morrow",
        "margin": 19283,
        "margin_pct": 15.23,
        "winner": "REP",
        "competitiveness": {
          "color": "#ef3b2c"
        }
      },
      "32": {
        "dem_votes": 71579,
        "rep_votes": 26928,
        "other_votes": 0,
        "total_votes": 98507,
        "dem_candidate": "Maurice (Mo) Green",
        "rep_candidate": "Michele Morrow",
        "margin": -44651,
        "margin_pct": -45.33,
        "winner": "DEM",
        "competitiveness": {
          "color": "#08306b"
        }
      },
      "33": {
        "dem_votes": 34763,
        "rep_votes": 73988,
        "other_votes": 0,
        "total_votes": 108751,
        "dem_candidate": "Maurice (Mo) Green",
        "rep_candidate": "Michele Morrow",
        "margin": 39225,
        "margin_pct": 36.07,
        "winner": "REP",
        "competitiveness": {
          "color": "#a50f15"
        }
      },
      "34": {
        "dem_votes": 53032,
        "rep_votes": 57822,
        "other_votes": 0,
        "total_votes": 110854,
        "dem_candidate": "Maurice (Mo) Green",
        "rep_candidate": "Michele Morrow",
        "margin": 4790,
        "margin_pct": 4.32,
        "winner": "REP",
        "competitiveness": {
          "color": "#fcae91"
        }
      },
      "35": {
        "dem_votes": 49701,
        "rep_votes": 78930,
        "other_votes": 0,
        "total_votes": 128631,
        "dem_candidate": "Maurice (Mo) Green",
        "rep_candidate": "Michele Morrow",
        "margin": 29229,
        "margin_pct": 22.72,
        "winner": "REP",
        "competitiveness": {
          "color": "#cb181d"
        }
      },
      "36": {
        "dem_votes": 29404,
        "rep_votes": 82504,
        "other_votes": 0,
        "total_votes": 111908,
        "dem_candidate": "Maurice (Mo) Green",
        "rep_candidate": "Michele Morrow",
        "margin": 53100,
        "margin_pct": 47.45,
        "winner": "REP",
        "competitiveness": {
          "color": "#67000d"
        }
      },
      "37": {
        "dem_votes": 49317,
        "rep_votes": 78877,
        "other_votes": 0,
        "total_votes": 128194,
        "dem_candidate": "Maurice (Mo) Green",
        "rep_candidate": "Michele Morrow",
        "margin": 29560,
        "margin_pct": 23.06,
        "winner": "REP",
        "competitiveness": {
          "color": "#cb181d"
        }
      },
      "38": {
        "dem_votes": 81350,
        "rep_votes": 35598,
        "other_votes": 0,
        "total_votes": 116948,
        "dem_candidate": "Maurice (Mo) Green",
        "rep_candidate": "Michele Morrow",
        "margin": -45752,
        "margin_pct": -39.12,
        "winner": "DEM",
        "competitiveness": {
          "color": "#08519c"
        }
      },
      "39": {
        "dem_votes": 73337,
        "rep_votes": 34753,
        "other_votes": 0,
        "total_votes": 108090,
        "dem_candidate": "Maurice (Mo) Green",
        "rep_candidate": "Michele Morrow",
        "margin": -38584,
        "margin_pct": -35.7,
        "winner": "DEM",
        "competitiveness": {
          "color": "#08519c"
        }
      },
      "40": {
        "dem_votes": 68832,
        "rep_votes": 21072,
        "other_votes": 0,
        "total_votes": 89904,
        "dem_candidate": "Maurice (Mo) Green",
        "rep_candidate": "Michele Morrow",
        "margin": -47760,
        "margin_pct": -53.12,
        "winner": "DEM",
        "competitiveness": {
          "color": "#08306b"
        }
      },
      "41": {
        "dem_votes": 84837,
        "rep_votes": 24615,
        "other_votes": 0,
        "total_votes": 109452,
        "dem_candidate": "Maurice (Mo) Green",
        "rep_candidate": "Michele Morrow",
        "margin": -60222,
        "margin_pct": -55.02,
        "winner": "DEM",
        "competitiveness": {
          "color": "#08306b"
        }
      },
      "42": {
        "dem_votes": 64730,
        "rep_votes": 56861,
        "other_votes": 0,
        "total_votes": 121591,
        "dem_candidate": "Maurice (Mo) Green",
        "rep_candidate": "Michele Morrow",
        "margin": -7869,
        "margin_pct": -6.47,
        "winner": "DEM",
        "competitiveness": {
          "color": "#9ecae1"
        }
      },
      "43": {
        "dem_votes": 41837,
        "rep_votes": 66109,
        "other_votes": 0,
        "total_votes": 107946,
        "dem_candidate": "Maurice (Mo) Green",
        "rep_candidate": "Michele Morrow",
        "margin": 24272,
        "margin_pct": 22.49,
        "winner": "REP",
        "competitiveness": {
          "color": "#cb181d"
        }
      },
      "44": {
        "dem_votes": 37414,
        "rep_votes": 74815,
        "other_votes": 0,
        "total_votes": 112229,
        "dem_candidate": "Maurice (Mo) Green",
        "rep_candidate": "Michele Morrow",
        "margin": 37401,
        "margin_pct": 33.33,
        "winner": "REP",
        "competitiveness": {
          "color": "#a50f15"
        }
      },
      "45": {
        "dem_votes": 35723,
        "rep_votes": 77233,
        "other_votes": 0,
        "total_votes": 112956,
        "dem_candidate": "Maurice (Mo) Green",
        "rep_candidate": "Michele Morrow",
        "margin": 41510,
        "margin_pct": 36.75,
        "winner": "REP",
        "competitiveness": {
          "color": "#a50f15"
        }
      },
      "46": {
        "dem_votes": 38228,
        "rep_votes": 67124,
        "other_votes": 0,
        "total_votes": 105352,
        "dem_candidate": "Maurice (Mo) Green",
        "rep_candidate": "Michele Morrow",
        "margin": 28896,
        "margin_pct": 27.43,
        "winner": "REP",
        "competitiveness": {
          "color": "#cb181d"
        }
      },
      "47": {
        "dem_votes": 45316,
        "rep_votes": 74231,
        "other_votes": 0,
        "total_votes": 119547,
        "dem_candidate": "Maurice (Mo) Green",
        "rep_candidate": "Michele Morrow",
        "margin": 28915,
        "margin_pct": 24.19,
        "winner": "REP",
        "competitiveness": {
          "color": "#cb181d"
        }
      },
      "48": {
        "dem_votes": 44125,
        "rep_votes": 71099,
        "other_votes": 0,
        "total_votes": 115224,
        "dem_candidate": "Maurice (Mo) Green",
        "rep_candidate": "Michele Morrow",
        "margin": 26974,
        "margin_pct": 23.41,
        "winner": "REP",
        "competitiveness": {
          "color": "#cb181d"
        }
      },
      "49": {
        "dem_votes": 81129,
        "rep_votes": 36039,
        "other_votes": 0,
        "total_votes": 117168,
        "dem_candidate": "Maurice (Mo) Green",
        "rep_candidate": "Michele Morrow",
        "margin": -45090,
        "margin_pct": -38.48,
        "winner": "DEM",
        "competitiveness": {
          "color": "#08519c"
        }
      },
      "50": {
        "dem_votes": 46129,
        "rep_votes": 78877,
        "other_votes": 0,
        "total_votes": 125006,
        "dem_candidate": "Maurice (Mo) Green",
        "rep_candidate": "Michele Morrow",
        "margin": 32748,
        "margin_pct": 26.2,
        "winner": "REP",
        "competitiveness": {
          "color": "#cb181d"
        }
      }
    }
  }
}
